[{"oid":562,"lemma":"Ακουβ","translitR":"akouv","score":6.648,"n":4,"verses":[{"b":"1ch","c":9,"v":17},{"b":"esd","c":2,"v":42},{"b":"neh","c":11,"v":19},{"b":"neh","c":7,"v":45}]},{"oid":8931,"lemma":"ναθινιμ","translitR":"nathinim","score":6.178,"n":5,"verses":[{"b":"esd","c":2,"v":70},{"b":"esd","c":7,"v":7},{"b":"esd","c":7,"v":24},{"b":"neh","c":10,"v":29},{"b":"neh","c":7,"v":73}]},{"oid":24,"lemma":"Αβδεδομ","translitR":"avdédom","score":5.667,"n":3,"verses":[{"b":"1ch","c":15,"v":18},{"b":"1ch","c":15,"v":24},{"b":"1ch","c":16,"v":38}]},{"oid":291,"lemma":"ᾄδω","translitR":"adô","score":5.064,"n":11,"verses":[{"b":"esd","c":10,"v":24},{"b":"esd","c":2,"v":70},{"b":"esd","c":7,"v":7},{"b":"esd","c":7,"v":24},{"b":"neh","c":10,"v":29},{"b":"neh","c":10,"v":40},{"b":"neh","c":12,"v":45},{"b":"neh","c":12,"v":47},{"b":"neh","c":13,"v":5},{"b":"neh","c":7,"v":1},{"b":"neh","c":7,"v":73}]},{"oid":5692,"lemma":"Ζαχαρίας","translitR":"zakharias","score":3.944,"n":3,"verses":[{"b":"1ch","c":15,"v":18},{"b":"1ch","c":15,"v":24},{"b":"1ch","c":9,"v":21}]},{"oid":1328,"lemma":"ἀπαρχή","translitR":"aparkhi","score":3.826,"n":3,"verses":[{"b":"2ch","c":31,"v":14},{"b":"neh","c":10,"v":40},{"b":"neh","c":13,"v":5}]},{"oid":7945,"lemma":"Λευΐτης","translitR":"lévitis","score":3.794,"n":13,"verses":[{"b":"2ch","c":31,"v":14},{"b":"2ch","c":34,"v":13},{"b":"2ch","c":35,"v":15},{"b":"2ch","c":8,"v":14},{"b":"esd","c":2,"v":70},{"b":"esd","c":7,"v":7},{"b":"esd","c":7,"v":24},{"b":"neh","c":10,"v":29},{"b":"neh","c":12,"v":30},{"b":"neh","c":12,"v":47},{"b":"neh","c":13,"v":5},{"b":"neh","c":7,"v":1},{"b":"neh","c":7,"v":73}]},{"oid":4660,"lemma":"ἐντολή","translitR":"éntoli","score":2.837,"n":4,"verses":[{"b":"2ch","c":35,"v":15},{"b":"2ch","c":8,"v":14},{"b":"neh","c":12,"v":45},{"b":"neh","c":13,"v":5}]},{"oid":4011,"lemma":"ἑκατόν","translitR":"hékaton","score":2.618,"n":3,"verses":[{"b":"esd","c":2,"v":42},{"b":"neh","c":11,"v":19},{"b":"neh","c":7,"v":45}]},{"oid":10819,"lemma":"πύλη","translitR":"puli","score":2.594,"n":4,"verses":[{"b":"2ch","c":23,"v":19},{"b":"2ch","c":35,"v":15},{"b":"2ch","c":8,"v":14},{"b":"job","c":38,"v":17}]},{"oid":6436,"lemma":"ἱερεύς","translitR":"hiéréfs","score":2.531,"n":10,"verses":[{"b":"1ch","c":15,"v":24},{"b":"2ch","c":8,"v":14},{"b":"esd","c":2,"v":70},{"b":"esd","c":7,"v":7},{"b":"esd","c":7,"v":24},{"b":"neh","c":10,"v":29},{"b":"neh","c":10,"v":40},{"b":"neh","c":12,"v":30},{"b":"neh","c":13,"v":5},{"b":"neh","c":7,"v":73}]},{"oid":242,"lemma":"ἀδελφός","translitR":"adélfos","score":1.837,"n":5,"verses":[{"b":"1ch","c":15,"v":18},{"b":"1ch","c":16,"v":38},{"b":"1ch","c":9,"v":17},{"b":"2ch","c":35,"v":15},{"b":"neh","c":11,"v":19}]}]