[{"oid":5820,"lemma":"Ηλιου","translitR":"iliou","score":5.745,"n":4,"verses":[{"b":"1ki","c":19,"v":13},{"b":"2ki","c":2,"v":8},{"b":"2ki","c":2,"v":13},{"b":"2ki","c":2,"v":14}]},{"oid":4348,"lemma":"Ελισαιε","translitR":"éliséé","score":5.355,"n":3,"verses":[{"b":"1ki","c":19,"v":19},{"b":"2ki","c":2,"v":13},{"b":"2ki","c":2,"v":14}]},{"oid":4500,"lemma":"ἐν","translitR":"én","score":0.61,"n":3,"verses":[{"b":"1ki","c":19,"v":13},{"b":"1ki","c":19,"v":19},{"b":"2ki","c":2,"v":8}]},{"oid":2102,"lemma":"αὐτός","translitR":"aftos","score":0.447,"n":4,"verses":[{"b":"1ki","c":19,"v":13},{"b":"1ki","c":19,"v":19},{"b":"2ki","c":2,"v":8},{"b":"2ki","c":2,"v":14}]},{"oid":6842,"lemma":"καί","translitR":"ké","score":0.217,"n":5,"verses":[{"b":"1ki","c":19,"v":13},{"b":"1ki","c":19,"v":19},{"b":"2ki","c":2,"v":8},{"b":"2ki","c":2,"v":13},{"b":"2ki","c":2,"v":14}]},{"oid":9189,"lemma":"ὁ","translitR":"ho","score":0.158,"n":5,"verses":[{"b":"1ki","c":19,"v":13},{"b":"1ki","c":19,"v":19},{"b":"2ki","c":2,"v":8},{"b":"2ki","c":2,"v":13},{"b":"2ki","c":2,"v":14}]}]