[{"b":"2sa","c":21,"v":10,"w":630,"f":"πετεινὰ"},{"b":"1ki","c":5,"v":13,"w":390,"f":"πετεινῶν"},{"b":"1ki","c":12,"v":24,"w":2210,"f":"πετεινὰ"},{"b":"1ki","c":16,"v":4,"w":178,"f":"πετεινὰ"},{"b":"1ki","c":20,"v":24,"w":1168,"f":"πετεινὰ"},{"b":"est","c":8,"v":12,"w":1520,"f":"πετεινοῖς"},{"b":"jdt","c":11,"v":7,"w":378,"f":"πετεινὰ"},{"b":"4ma","c":14,"v":15,"w":484,"f":"πετεινῶν"},{"b":"psa","c":8,"v":9,"w":220,"f":"πετεινὰ"},{"b":"psa","c":49,"v":11,"w":284,"f":"πετεινὰ"},{"b":"psa","c":77,"v":27,"w":754,"f":"πετεινὰ"},{"b":"psa","c":78,"v":2,"w":58,"f":"πετεινοῖς"},{"b":"psa","c":103,"v":12,"w":272,"f":"πετεινὰ"},{"b":"psa","c":148,"v":10,"w":244,"f":"πετεινὰ"},{"b":"oda","c":8,"v":80,"w":802,"f":"πετεινὰ"},{"b":"ecc","c":10,"v":20,"w":556,"f":"πετεινὸν"},{"b":"job","c":12,"v":7,"w":136,"f":"πετεινὰ"},{"b":"job","c":28,"v":7,"w":140,"f":"πετεινόν"},{"b":"job","c":28,"v":21,"w":442,"f":"πετεινῶν"},{"b":"job","c":35,"v":11,"w":228,"f":"πετεινῶν"},{"b":"sir","c":11,"v":3,"w":52,"f":"πετεινοῖς"},{"b":"sir","c":17,"v":4,"w":92,"f":"πετεινῶν"},{"b":"sir","c":22,"v":20,"w":502,"f":"πετεινὰ"},{"b":"sir","c":27,"v":9,"w":180,"f":"πετεινὰ"},{"b":"sir","c":27,"v":19,"w":412,"f":"πετεινὸν"},{"b":"sir","c":43,"v":14,"w":316,"f":"πετεινά"},{"b":"sir","c":43,"v":18,"w":382,"f":"πετεινὰ"},{"b":"pss","c":5,"v":9,"w":264,"f":"πετεινὰ"},{"b":"hos","c":2,"v":14,"w":760,"f":"πετεινὰ"},{"b":"hos","c":2,"v":20,"w":1040,"f":"πετεινῶν"},{"b":"hos","c":4,"v":3,"w":140,"f":"πετεινοῖς"},{"b":"hos","c":7,"v":12,"w":442,"f":"πετεινὰ"},{"b":"zep","c":1,"v":3,"w":74,"f":"πετεινὰ"},{"b":"isa","c":16,"v":2,"w":32,"f":"πετεινοῦ"},{"b":"isa","c":18,"v":6,"w":222,"f":"πετεινοῖς"},{"b":"isa","c":18,"v":6,"w":248,"f":"πετεινὰ"},{"b":"isa","c":46,"v":11,"w":384,"f":"πετεινὸν"},{"b":"jer","c":4,"v":25,"w":1000,"f":"πετεινὰ"},{"b":"jer","c":5,"v":27,"w":1124,"f":"πετεινῶν"},{"b":"jer","c":7,"v":33,"w":1458,"f":"πετεινοῖς"},{"b":"jer","c":9,"v":9,"w":368,"f":"πετεινῶν"},{"b":"jer","c":12,"v":4,"w":160,"f":"πετεινά"},{"b":"jer","c":15,"v":3,"w":176,"f":"πετεινὰ"},{"b":"jer","c":16,"v":4,"w":162,"f":"πετεινοῖς"},{"b":"jer","c":19,"v":7,"w":432,"f":"πετεινοῖς"},{"b":"jer","c":41,"v":20,"w":948,"f":"πετεινοῖς"},{"b":"ezk","c":17,"v":23,"w":1076,"f":"πετεινὸν"},{"b":"ezk","c":29,"v":5,"w":260,"f":"πετεινοῖς"},{"b":"ezk","c":31,"v":6,"w":222,"f":"πετεινὰ"},{"b":"ezk","c":31,"v":13,"w":596,"f":"πετεινὰ"},{"b":"ezk","c":32,"v":4,"w":178,"f":"πετεινὰ"},{"b":"ezk","c":38,"v":20,"w":940,"f":"πετεινὰ"},{"b":"ezk","c":39,"v":4,"w":180,"f":"πετεινῷ"},{"b":"ezk","c":39,"v":17,"w":766,"f":"πετεινῷ"},{"b":"ezk","c":44,"v":31,"w":1636,"f":"πετεινῶν"},{"b":"dan","c":2,"v":38,"w":1800,"f":"πετεινὰ"},{"b":"dan","c":3,"v":80,"w":2956,"f":"πετεινὰ"},{"b":"dan","c":7,"v":6,"w":258,"f":"πετεινοῦ"}]