[{"b":"gen","c":43,"v":21,"w":976,"f":"σταθμῷ"},{"b":"exo","c":12,"v":7,"w":246,"f":"σταθμῶν"},{"b":"exo","c":12,"v":22,"w":1024,"f":"σταθμῶν"},{"b":"exo","c":12,"v":23,"w":1100,"f":"σταθμῶν"},{"b":"exo","c":21,"v":6,"w":212,"f":"σταθμόν"},{"b":"lev","c":26,"v":26,"w":1054,"f":"σταθμῷ"},{"b":"lev","c":27,"v":3,"w":82,"f":"σταθμῷ"},{"b":"num","c":33,"v":1,"w":4,"f":"σταθμοὶ"},{"b":"num","c":33,"v":2,"w":54,"f":"σταθμοὺς"},{"b":"num","c":33,"v":2,"w":68,"f":"σταθμοὶ"},{"b":"jdg","c":8,"v":26,"w":1174,"f":"σταθμὸς"},{"b":"jdg","c":16,"v":3,"w":142,"f":"σταθμοῖς"},{"b":"1sa","c":17,"v":5,"w":194,"f":"σταθμὸς"},{"b":"2sa","c":12,"v":30,"w":1594,"f":"σταθμὸς"},{"b":"2sa","c":21,"v":16,"w":988,"f":"σταθμὸς"},{"b":"1ki","c":7,"v":32,"w":1486,"f":"σταθμὸς"},{"b":"1ki","c":7,"v":32,"w":1518,"f":"σταθμῷ"},{"b":"1ki","c":10,"v":14,"w":730,"f":"σταθμὸς"},{"b":"2ki","c":12,"v":10,"w":460,"f":"σταθμὸν"},{"b":"2ki","c":22,"v":4,"w":192,"f":"σταθμὸν"},{"b":"2ki","c":23,"v":4,"w":284,"f":"σταθμὸν"},{"b":"2ki","c":25,"v":16,"w":686,"f":"σταθμὸς"},{"b":"2ki","c":25,"v":18,"w":824,"f":"σταθμὸν"},{"b":"1ch","c":20,"v":2,"w":118,"f":"σταθμὸς"},{"b":"1ch","c":22,"v":3,"w":122,"f":"σταθμός"},{"b":"1ch","c":22,"v":14,"w":674,"f":"σταθμός"},{"b":"1ch","c":28,"v":14,"w":842,"f":"σταθμὸν"},{"b":"1ch","c":28,"v":16,"w":884,"f":"σταθμὸν"},{"b":"1ch","c":28,"v":17,"w":932,"f":"σταθμὸν"},{"b":"1ch","c":28,"v":17,"w":948,"f":"σταθμοῦ"},{"b":"1ch","c":28,"v":18,"w":968,"f":"σταθμὸν"},{"b":"2ch","c":9,"v":13,"w":674,"f":"σταθμὸς"},{"b":"esd","c":8,"v":30,"w":1164,"f":"σταθμὸν"},{"b":"esd","c":8,"v":34,"w":1380,"f":"σταθμῷ"},{"b":"esd","c":8,"v":34,"w":1394,"f":"σταθμός"},{"b":"pro","c":8,"v":34,"w":772,"f":"σταθμοὺς"},{"b":"job","c":28,"v":25,"w":530,"f":"σταθμὸν"},{"b":"wis","c":11,"v":20,"w":522,"f":"σταθμῷ"},{"b":"sir","c":6,"v":15,"w":334,"f":"σταθμὸς"},{"b":"sir","c":16,"v":25,"w":604,"f":"σταθμῷ"},{"b":"sir","c":26,"v":15,"w":374,"f":"σταθμὸς"},{"b":"sir","c":28,"v":25,"w":666,"f":"σταθμὸν"},{"b":"sir","c":42,"v":7,"w":144,"f":"σταθμῷ"},{"b":"pss","c":5,"v":4,"w":128,"f":"σταθμῷ"},{"b":"isa","c":28,"v":17,"w":658,"f":"σταθμούς"},{"b":"isa","c":40,"v":12,"w":410,"f":"σταθμῷ"},{"b":"isa","c":46,"v":6,"w":190,"f":"σταθμῷ"},{"b":"isa","c":57,"v":8,"w":242,"f":"σταθμῶν"},{"b":"jer","c":9,"v":1,"w":12,"f":"σταθμὸν"},{"b":"jer","c":52,"v":20,"w":810,"f":"σταθμὸς"},{"b":"ezk","c":4,"v":10,"w":526,"f":"σταθμῷ"},{"b":"ezk","c":4,"v":16,"w":788,"f":"σταθμῷ"}]