[{"oid":3838,"lemma":"Παῦλος","translitR":"pavlos","score":2.842,"n":3,"verses":[{"b":"ac","c":15,"v":35},{"b":"ac","c":25,"v":6},{"b":"ac","c":25,"v":14}]},{"oid":2235,"lemma":"ἡμέρα","translitR":"himéra","score":2.259,"n":4,"verses":[{"b":"ac","c":16,"v":12},{"b":"ac","c":20,"v":6},{"b":"ac","c":25,"v":6},{"b":"ac","c":25,"v":14}]},{"oid":4049,"lemma":"πολύς","translitR":"polus","score":1.947,"n":3,"verses":[{"b":"ac","c":15,"v":35},{"b":"ac","c":25,"v":6},{"b":"ac","c":25,"v":14}]},{"oid":3205,"lemma":"μετά","translitR":"méta","score":1.788,"n":3,"verses":[{"b":"jn","c":3,"v":22},{"b":"ac","c":15,"v":35},{"b":"ac","c":20,"v":6}]},{"oid":1508,"lemma":"εἰς","translitR":"is","score":1.077,"n":5,"verses":[{"b":"jn","c":3,"v":22},{"b":"ac","c":12,"v":19},{"b":"ac","c":16,"v":12},{"b":"ac","c":20,"v":6},{"b":"ac","c":25,"v":6}]},{"oid":1156,"lemma":"δέ","translitR":"dé","score":0.918,"n":7,"verses":[{"b":"ac","c":12,"v":19},{"b":"ac","c":14,"v":28},{"b":"ac","c":15,"v":35},{"b":"ac","c":16,"v":12},{"b":"ac","c":20,"v":6},{"b":"ac","c":25,"v":6},{"b":"ac","c":25,"v":14}]},{"oid":1710,"lemma":"ἐν","translitR":"én","score":0.23,"n":3,"verses":[{"b":"ac","c":15,"v":35},{"b":"ac","c":16,"v":12},{"b":"ac","c":25,"v":6}]},{"oid":836,"lemma":"αὐτός","translitR":"aftos","score":0.173,"n":5,"verses":[{"b":"jn","c":3,"v":22},{"b":"ac","c":12,"v":19},{"b":"ac","c":14,"v":3},{"b":"ac","c":20,"v":6},{"b":"ac","c":25,"v":6}]},{"oid":3454,"lemma":"ὁ","translitR":"ho","score":0.131,"n":9,"verses":[{"b":"jn","c":3,"v":22},{"b":"ac","c":12,"v":19},{"b":"ac","c":14,"v":3},{"b":"ac","c":14,"v":28},{"b":"ac","c":15,"v":35},{"b":"ac","c":16,"v":12},{"b":"ac","c":20,"v":6},{"b":"ac","c":25,"v":6},{"b":"ac","c":25,"v":14}]}]