[{"b":"mt","c":27,"v":56,"w":1662,"f":"Μαγδαληνὴ"},{"b":"mt","c":27,"v":61,"w":1826,"f":"Μαγδαληνὴ"},{"b":"mt","c":28,"v":1,"w":22,"f":"Μαγδαληνὴ"},{"b":"mk","c":15,"v":40,"w":1074,"f":"Μαγδαληνὴ"},{"b":"mk","c":15,"v":47,"w":1322,"f":"Μαγδαληνὴ"},{"b":"mk","c":16,"v":1,"w":12,"f":"Μαγδαληνὴ"},{"b":"mk","c":16,"v":9,"w":358,"f":"Μαγδαληνῇ,"},{"b":"lk","c":8,"v":2,"w":76,"f":"Μαγδαληνή,"},{"b":"lk","c":24,"v":10,"w":244,"f":"Μαγδαληνὴ"},{"b":"jn","c":19,"v":25,"w":1000,"f":"Μαγδαληνή."},{"b":"jn","c":20,"v":1,"w":14,"f":"Μαγδαληνὴ"},{"b":"jn","c":20,"v":18,"w":644,"f":"Μαγδαληνὴ"}]