[{"b":"mt","c":17,"v":5,"w":172,"f":"νεφέλη"},{"b":"mt","c":17,"v":5,"w":190,"f":"νεφέλης"},{"b":"mt","c":24,"v":30,"w":934,"f":"νεφελῶν"},{"b":"mt","c":26,"v":64,"w":2142,"f":"νεφελῶν"},{"b":"mk","c":9,"v":7,"w":234,"f":"νεφέλη"},{"b":"mk","c":9,"v":7,"w":250,"f":"νεφέλης·"},{"b":"mk","c":13,"v":26,"w":854,"f":"νεφέλαις"},{"b":"mk","c":14,"v":62,"w":2028,"f":"νεφελῶν"},{"b":"lk","c":9,"v":34,"w":1268,"f":"νεφέλη"},{"b":"lk","c":9,"v":34,"w":1292,"f":"νεφέλην."},{"b":"lk","c":9,"v":35,"w":1304,"f":"νεφέλης"},{"b":"lk","c":12,"v":54,"w":1888,"f":"νεφέλην"},{"b":"lk","c":21,"v":27,"w":822,"f":"νεφέλῃ"},{"b":"ac","c":1,"v":9,"w":318,"f":"νεφέλη"},{"b":"1co","c":10,"v":1,"w":26,"f":"νεφέλην"},{"b":"1co","c":10,"v":2,"w":58,"f":"νεφέλῃ"},{"b":"1th","c":4,"v":17,"w":578,"f":"νεφέλαις"},{"b":"jud","c":1,"v":12,"w":468,"f":"νεφέλαι"},{"b":"re","c":1,"v":7,"w":302,"f":"νεφελῶν,"},{"b":"re","c":10,"v":1,"w":20,"f":"νεφέλην,"},{"b":"re","c":11,"v":12,"w":574,"f":"νεφέλῃ,"},{"b":"re","c":14,"v":14,"w":734,"f":"νεφέλη"},{"b":"re","c":14,"v":14,"w":744,"f":"νεφέλην"},{"b":"re","c":14,"v":15,"w":812,"f":"νεφέλης·"},{"b":"re","c":14,"v":16,"w":860,"f":"νεφέλης"}]